squid/foo.py
squid-0.2.0.dist-info/WHEEL
squid-0.2.0.dist-info/METADATA
squid-0.2.0.dist-info/RECORD
