Metadata-Version: 2.1
Name: squid
Version: 0.2.0
Summary: Coming soon!
Author: PierreGuilmin
Author-email: pierreguilmin@gmail.com
Requires-Python: >=3.8,<4.0
Classifier: Programming Language :: Python :: 3
Classifier: Programming Language :: Python :: 3.8
Classifier: Programming Language :: Python :: 3.9
